pyav_test.py
pyav_test-0.0.1.dist-info/LICENSE.txt
pyav_test-0.0.1.dist-info/METADATA
pyav_test-0.0.1.dist-info/WHEEL
pyav_test-0.0.1.dist-info/top_level.txt
pyav_test-0.0.1.dist-info/RECORD
