Metadata-Version: 2.1
Name: pyav-test
Version: 0.0.1
Summary: A GUI Music Player with all the basic functions, which is developed using Tkinter
Author: Akash V
Keywords: Test
Classifier: Programming Language :: Python :: 3
Classifier: License :: OSI Approved :: MIT License
Classifier: Operating System :: OS Independent
Requires-Python: >=3.6
License-File: LICENSE.txt
